jax_ik/__init__.py
jax_ik/hand_specification.py
jax_ik/helper.py
jax_ik/ik.py
jax_ik/objectives.py
jax_ik/smplx_statics.py
jax_ik-0.1.6.dist-info/METADATA
jax_ik-0.1.6.dist-info/WHEEL
jax_ik-0.1.6.dist-info/top_level.txt
jax_ik-0.1.6.dist-info/RECORD
