Metadata-Version: 2.4
Name: jax-ik
Version: 0.1.6
Summary: Real-Time Inverse Kinematics for Generating Multi-Constrained Movements of Virtual Human Characters
Author-email: Hendric Voss <hvoss@techfak.uni-bielefeld.de>
License: CC BY-NC-SA 4.0
Requires-Python: >=3.10
Requires-Dist: numpy>=1.19.0
Requires-Dist: jax>=0.6.2
Requires-Dist: jax-cuda12-plugin
Requires-Dist: configargparse>=1.7
Requires-Dist: pyvista>=0.45.2
Requires-Dist: pygltflib>=1.16.3
Requires-Dist: urchin>=0.0.29
Requires-Dist: trimesh>=4.6.4
Requires-Dist: tqdm>=4.67.1
Requires-Dist: networkx>=3.4
Requires-Dist: rtree>=1.4.0
Requires-Dist: mesh_to_sdf>=0.0.15
Requires-Dist: trimesh
